{
  "head": "Ниже приведены реквизиты компании, в случае необходимости получения дополнительных документов: свидетельства о государственной регистрации, идентификационного номера налогоплательщика вы можете обратиться в бухгалтерию предприятия.",
  "items": [
    {
      "title": "Полное наименование:",
      "value": "Общество с ограниченной ответственностью «Медикс»"
    },
    {
      "title": "Сокращенное наименование:",
      "value": "ООО «Медикс»"
    },
    {
      "title": "ИНН/КПП:",
      "value": "3702182205/370201001"
    },
    {
      "title": "ОРГН:",
      "value": "1173702016124"
    },
    {
      "title": "Юридический адрес:",
      "value": "153021, г. Иваново, ул. Поляковой, д. 8, литер А-46, офис 209"
    },
    {
      "title": "Почтовый адрес:",
      "value": "153021, г. Иваново, ул. Поляковой, д. 8, литер А-46, офис 209"
    },
    {
      "title": "Адрес места оказания услуг:",
      "value": "153000, г. Иваново, пл.Пушкина 12"
    },
    {
      "title": "Телефон, факс:",
      "numbers": ["8 800 775 02 05", "8(4932)24-51-21"]
    },
    {
      "title": "Электронная почта:",
      "mail": "mail@medikslab.ru"
    },
    {
      "title": "Сайт:",
      "value": "medikslab.ru"
    },
    {
      "title": "Банковские реквизиты:",
      "value": "БИК 047888760<br>р/сч. № 40702810902000038063 в Ярославском филиале ПАО «Промсвязьбанк» г. Ярославль, корр.сч. № 30101810300000000760"
    }
  ]
}
